fastapi_amis/__init__.py
fastapi_amis/amis/__init__.py
fastapi_amis/amis/components.py
fastapi_amis/amis/constants.py
fastapi_amis/amis/types.py
fastapi_amis/amis/templates/app.jinja2
fastapi_amis/amis/templates/page.jinja2
fastapi_amis/core/__init__.py
fastapi_amis/core/router.py
fastapi_amis/core/site.py
fastapi_amis/core/views.py
fastapi_amis/extensions/__init__.py
fastapi_amis/extensions/admin.py
fastapi_amis/extensions/exception.py
fastapi_amis-0.0.1.dist-info/METADATA
fastapi_amis-0.0.1.dist-info/WHEEL
fastapi_amis-0.0.1.dist-info/licenses/LICENSE
fastapi_amis-0.0.1.dist-info/RECORD
