Metadata-Version: 2.4
Name: fastapi-amis
Version: 0.0.1
Summary: FastAPI Amis
Project-URL: Homepage, https://github.com/InfernalAzazel/fastapi-amis
Project-URL: Documentation, https://infernalazazel.github.io/fastapi-amis/
Project-URL: Repository, https://github.com/InfernalAzazel/fastapi-amis
Author-email: kylin <260987762@qq.com>
License: Apache-2.0
License-File: LICENSE
Classifier: Environment :: Web Environment
Classifier: Framework :: AsyncIO
Classifier: Framework :: FastAPI
Classifier: Framework :: Pydantic
Classifier: Framework :: Pydantic :: 2
Classifier: Intended Audience :: Information Technology
Classifier: Intended Audience :: System Administrators
Classifier: License :: OSI Approved :: Apache Software License
Classifier: Operating System :: OS Independent
Classifier: Programming Language :: Python
Classifier: Programming Language :: Python :: 3
Classifier: Programming Language :: Python :: 3.10
Classifier: Programming Language :: Python :: 3.11
Classifier: Programming Language :: Python :: 3.12
Classifier: Topic :: Internet
Classifier: Topic :: Software Development
Classifier: Topic :: Software Development :: Libraries
Classifier: Topic :: Software Development :: Libraries :: Application Frameworks
Classifier: Topic :: Software Development :: Libraries :: Python Modules
Classifier: Typing :: Typed
Requires-Python: >=3.10
Provides-Extra: dev
Requires-Dist: fastapi-users[beanie]>=14.0.1; extra == 'dev'
Requires-Dist: fastapi[standard]>=0.117.1; extra == 'dev'
Requires-Dist: httpx>=0.28.1; extra == 'dev'
Requires-Dist: jinja2>=3.1.6; extra == 'dev'
Requires-Dist: mkdocs-material>=9.6.21; extra == 'dev'
Requires-Dist: pydantic-settings>=2.11.0; extra == 'dev'
Requires-Dist: pydantic<2.10.0,>=2.5.0; extra == 'dev'
Requires-Dist: pytest-asyncio>=1.2.0; extra == 'dev'
Requires-Dist: pytest>=8.4.2; extra == 'dev'
Requires-Dist: ujson>=5.11.0; extra == 'dev'
